{"cameraMode":{"drawMode":0,"name":"Shaded","section":"Shading Mode"},"sceneLighting":false,"audioPlay":false,"sceneViewState":{"showFog":true,"showMaterialUpdate":false,"showSkybox":false,"showFlares":true,"showImageEffects":true,"showParticleSystems":true},"in2DMode":false,"pivot":{"x":5.513027667999268,"y":6.417945861816406,"z":-16.685762405395509},"rotation":{"x":-0.047049812972545627,"y":-0.19645917415618897,"z":0.009420424699783326,"w":-0.9793868660926819},"size":0.6423606872558594,"orthographic":false}